AnyCADQt5/PyAnyQt.py
AnyCADQt5/PyAnyQt5.py
AnyCADQt5/__init__.py
PyAnyCADQt5-2024.4.1.dist-info/METADATA
PyAnyCADQt5-2024.4.1.dist-info/WHEEL
PyAnyCADQt5-2024.4.1.dist-info/top_level.txt
PyAnyCADQt5-2024.4.1.dist-info/RECORD
